tinygraphio/__init__.py
tinygraphio/errors.py
tinygraphio/graph.py
tinygraphio/proto/tinygraphio_pb2.py
tinygraphio/py.typed
tinygraphio/reader.py
tinygraphio/scripts/__init__.py
tinygraphio/scripts/__main__.py
tinygraphio/scripts/version.py
tinygraphio/utils.py
tinygraphio/writer.py
tinygraphio-1.0.0.dist-info/entry_points.txt
tinygraphio-1.0.0.dist-info/WHEEL
tinygraphio-1.0.0.dist-info/LICENSE.md
tinygraphio-1.0.0.dist-info/METADATA
tinygraphio-1.0.0.dist-info/RECORD
