Metadata-Version: 2.1
Name: tinygraphio
Version: 1.0.0
Summary: The tinygraphio graph data interchange file format
License: MIT
Author: tinygraph
Author-email: hello@tinygraph.org
Requires-Python: >3.8,<=4
Classifier: License :: OSI Approved :: MIT License
Classifier: Programming Language :: Python :: 3
Classifier: Programming Language :: Python :: 3.9
Classifier: Programming Language :: Python :: 3.10
Classifier: Programming Language :: Python :: 3.11
Requires-Dist: protobuf (>=4.21.12,<5.0.0)
